value_factory/__init__.py
value_factory/version.py
value_factory/api/catalog.py
value_factory/api/constant.py
value_factory/api/extension.py
value_factory/api/task.py
value_factory/api/type.py
value_factory/catalog/checking.py
value_factory/catalog/factory.py
value_factory/catalog/annotation/boolean.py
value_factory/catalog/annotation/callable.py
value_factory/catalog/annotation/choices.py
value_factory/catalog/annotation/collection.py
value_factory/catalog/annotation/number.py
value_factory/catalog/annotation/path.py
value_factory/constant/console.py
value_factory/constant/value.py
value_factory/extension/hint.py
value_factory/task/casting.py
value_factory/type/annotation.py
value_factory/type/checking.py
value_factory/type/factory.py
value_factory/type/hint.py
value_factory/type/value.py
value_factory-2025.11.dist-info/METADATA
value_factory-2025.11.dist-info/WHEEL
value_factory-2025.11.dist-info/top_level.txt
value_factory-2025.11.dist-info/RECORD
