Metadata-Version: 2.4
Name: value-factory
Version: 2025.11
Summary: Convert strings to Python objects, or cast objects, guided by (potentially annotated) type hints
Home-page: https://src.koda.cnrs.fr/eric.debreuve/value-factory/
Author: Eric Debreuve
Author-email: eric.debreuve@cnrs.fr
License: CeCILL-2.1
Project-URL: Documentation, https://src.koda.cnrs.fr/eric.debreuve/value-factory/-/wikis/home
Project-URL: Source, https://src.koda.cnrs.fr/eric.debreuve/value-factory/
Keywords: str,character string,Python object,conversion,cast,type hint,type annotation
Classifier: Topic :: Software Development
Classifier: Intended Audience :: Developers
Classifier: License :: OSI Approved :: CEA CNRS Inria Logiciel Libre License, version 2.1 (CeCILL-2.1)
Classifier: Programming Language :: Python :: 3
Classifier: Development Status :: 4 - Beta
Requires-Python: >=3.11
Requires-Dist: logger-36
Dynamic: author
Dynamic: author-email
Dynamic: classifier
Dynamic: description
Dynamic: description-content-type
Dynamic: home-page
Dynamic: keywords
Dynamic: license
Dynamic: project-url
Dynamic: requires-dist
Dynamic: requires-python
Dynamic: summary
